nose_extra_tools.py
nose_extra_tools-1.0.2.dist-info/AUTHORS
nose_extra_tools-1.0.2.dist-info/LICENSE
nose_extra_tools-1.0.2.dist-info/METADATA
nose_extra_tools-1.0.2.dist-info/WHEEL
nose_extra_tools-1.0.2.dist-info/top_level.txt
nose_extra_tools-1.0.2.dist-info/RECORD
