Metadata-Version: 2.1
Name: nose-extra-tools
Version: 1.0.2
Summary: Extra testing goodies for nose.tools
Home-page: https://github.com/petarmaric/nose_extra_tools
Author: Petar Maric
Author-email: petarmaric@uns.ac.rs
License: BSD
Platform: any
Classifier: Development Status :: 5 - Production/Stable
Classifier: Intended Audience :: Developers
Classifier: License :: OSI Approved :: BSD License
Classifier: Operating System :: OS Independent
Classifier: Programming Language :: Python :: 2.6
Classifier: Programming Language :: Python :: 2.7
Classifier: Topic :: Software Development :: Testing
Classifier: Topic :: Utilities
Requires-Dist: nose (>=1.0)
